metoppy/__init__.py
metoppy/juliapkg.json
metoppy/metopreader.py
metoppy/tests/__init__.py
metoppy/tests/test_basic_interface.py
metoppy-0.1.0.dist-info/METADATA
metoppy-0.1.0.dist-info/WHEEL
metoppy-0.1.0.dist-info/licenses/LICENSE
metoppy-0.1.0.dist-info/RECORD
