Metadata-Version: 2.4
Name: metoppy
Version: 0.1.0
Summary: Python package wrapper of MetopDatasets.jl Julia package for reading products from the METOP satellites.
Project-URL: Homepage, https://github.com/eumetsat/MetopPy
Project-URL: Bug Tracker, https://github.com/eumetsat/MetopPy/issues
Project-URL: Documentation, https://github.com/eumetsat/MetopPy/blob/main/README.md
Project-URL: Source Code, https://github.com/eumetsat/MetopPy
Project-URL: Organization, https://github.com/eumetsat
Project-URL: Release Notes, https://github.com/eumetsat/MetopPy/blob/main/CHANGELOG.md
Author-email: Simon Kok Lupemba <simon.koklupemba@eumetsat.int>, Francesco Murdaca <francesco.murdaca@eumetsat.int>
Maintainer-email: Simon Kok Lupemba <simon.koklupemba@eumetsat.int>
License: MIT License
License-File: LICENSE
Classifier: Development Status :: 2 - Pre-Alpha
Classifier: Intended Audience :: Science/Research
Classifier: License :: OSI Approved :: MIT License
Classifier: Operating System :: OS Independent
Classifier: Programming Language :: Python
Classifier: Topic :: Scientific/Engineering
Requires-Python: >=3.11
Requires-Dist: juliacall>=0.9.14
Requires-Dist: juliapkg>=0.1.22
Provides-Extra: test
Requires-Dist: numpy==2.3.4; extra == 'test'
Requires-Dist: pre-commit==4.3.0; extra == 'test'
Requires-Dist: pytest-cov==7.0; extra == 'test'
Requires-Dist: pytest-html==4.1.1; extra == 'test'
Requires-Dist: pytest-mock==3.14.1; extra == 'test'
Requires-Dist: pytest==8.4.1; extra == 'test'
